sdf/__init__.py
sdf/core.py
sdf/d2.py
sdf/d3.py
sdf/dn.py
sdf/ease.py
sdf/mesh.py
sdf/progress.py
sdf/stl.py
sdf/text.py
sdf/util.py
sdflab-0.1.1.dist-info/LICENSE.md
sdflab-0.1.1.dist-info/METADATA
sdflab-0.1.1.dist-info/WHEEL
sdflab-0.1.1.dist-info/top_level.txt
sdflab-0.1.1.dist-info/RECORD
